{
  "en": {
    "title": "Progress Card",
    "description": "This is a card with progress bar."
  },
  "ja": {
    "title": "プログレスカード",
    "description": "これはプログレスカードです。"
  },
  "options": {
    "ignore": true,
    "container": {
      "centerContent": true,
      "p": "md"
    }
  },
  "authors": [
    {
      "id": 84060430,
      "login": "hirotomoyamada",
      "avatar_url": "https://avatars.githubusercontent.com/u/84060430?v=4",
      "html_url": "https://github.com/hirotomoyamada"
    }
  ]
}
